tsiparser/.ipynb_checkpoints/__init__-checkpoint.py
tsiparser/.ipynb_checkpoints/commons-checkpoint.py
tsiparser/.ipynb_checkpoints/tsiparser-checkpoint.py
tsiparser/__init__.py
tsiparser/assets/.ipynb_checkpoints/__init__-checkpoint.py
tsiparser/assets/__init__.py
tsiparser/assets/idcollection_dict.pickle
tsiparser/assets/summary_dict.pickle
tsiparser/commons.py
tsiparser/tsiparser.py
tsiparser-0.3.29.dist-info/LICENSE.txt
tsiparser-0.3.29.dist-info/METADATA
tsiparser-0.3.29.dist-info/WHEEL
tsiparser-0.3.29.dist-info/entry_points.txt
tsiparser-0.3.29.dist-info/RECORD
